Metadata-Version: 2.1
Name: s1290216-learn
Version: 1.0.1
Summary: This is homework
Home-page: https://github.com/s1290216/s1290216_learn
Author: s1290216
License: GPLv3
Platform: UNKNOWN
Classifier: Development Status :: 4 - Beta
Classifier: Programming Language :: Python :: 3
Classifier: License :: OSI Approved :: GNU General Public License v3 (GPLv3)
Classifier: Operating System :: OS Independent
Requires-Python: >=3.5
Requires-Dist: pami
Requires-Dist: plotly
